his/__init__.py
his/tory.py
his-0.0.1.dist-info/METADATA
his-0.0.1.dist-info/WHEEL
his-0.0.1.dist-info/top_level.txt
his-0.0.1.dist-info/RECORD
